Workbook

Sheet Calendar 
A2: September | C2: 2026 | D2: Attendance Tracker
D7: Employee ID | E7: Employee Name | F7: Cost Centre | G7: Designation | H7: Department | I7: =TEXT(I9,"ddd") -> Tue | J7: =TEXT(J9,"ddd") -> Wed | K7: =TEXT(K9,"ddd") -> Thu | L7: =TEXT(L9,"ddd") -> Fri | M7: =TEXT(M9,"ddd") -> Sat | N7: =TEXT(N9,"ddd") -> Sun | O7: =TEXT(O9,"ddd") -> Mon | P7: =TEXT(P9,"ddd") -> Tue | ... AM7: =TEXT(AM9,"ddd") -> EOM | AN7: =_xlfn.XLOOKUP('Calendar '!AN$9,Settings!$I6:$I17,Settings!$H6:$H17) -> Present | AO7: =_xlfn.XLOOKUP('Calendar '!AO$9,Settings!$I6:$I17,Settings!$H6:$H17) -> Earned Leave | AP7: =_xlfn.XLOOKUP('Calendar '!AP$9,Settings!$I6:$I17,Settings!$H6:$H17) -> Sick Leave | AQ7: =_xlfn.XLOOKUP('Calendar '!AQ$9,Settings!$I6:$I17,Settings!$H6:$H17) -> Maternity or Paternity | AR7: =_xlfn.XLOOKUP('Calendar '!AR$9,Settings!$I6:$I17,Settings!$H6:$H17) -> Half Day | AS7: =_xlfn.XLOOKUP('Calendar '!AS$9,Settings!$I6:$I17,Settings!$H6:$H17) -> Work From Home | AT7: =_xlfn.XLOOKUP('Calendar '!AT$9,Settings!$I6:$I17,Settings!$H6:$H17) -> Holidays | AU7: =_xlfn.XLOOKUP('Calendar '!AU$9,Settings!$I6:$I17,Settings!$H6:$H17) -> Week Offs | ... AY7: =_xlfn.XLOOKUP('Calendar '!AY$9,Settings!$I6:$I17,Settings!$H6:$H17) -> Short Leaves | AZ7: Total Leaves | BA7: Payable Days | BB7: Monthly Salary | BC7: Payable Salary | BD7: Actual Salary | BE7: Payable Sunday | BF7: Remark
I9: =DATEVALUE("1"&$A$2&$C$2) -> 46266 | J9: =IF(I$9<EOMONTH($I$9,0),I$9+1,"EOM") -> 46267 | K9: =IF(J$9<EOMONTH($I$9,0),J$9+1,"EOM") -> 46268 | L9: =IF(K$9<EOMONTH($I$9,0),K$9+1,"EOM") -> 46269 | M9: =IF(L$9<EOMONTH($I$9,0),L$9+1,"EOM") -> 46270 | N9: =IF(M$9<EOMONTH($I$9,0),M$9+1,"EOM") -> 46271 | O9: =IF(N$9<EOMONTH($I$9,0),N$9+1,"EOM") -> 46272 | P9: =IF(O$9<EOMONTH($I$9,0),O$9+1,"EOM") -> 46273 | Q9: =IF(P$9<EOMONTH($I$9,0),P$9+1,"EOM") -> 46274 | ... AM9: =IF(AL$9<EOMONTH($I$9,0),AL$9+1,"EOM") -> EOM | AN9: =Settings!I6 -> P | AO9: =Settings!I7 -> EL | AP9: =Settings!I8 -> SL | AQ9: =Table24[[#This Row],[Code]] -> MPL | AR9: =Settings!$I10 -> HD | AS9: =Settings!$I11 -> WFH | AT9: =Settings!$I12 -> H | AU9: =Settings!$I13 -> WO | AV9: =Settings!$I14 -> A | AW9: =Settings!$I15 -> LT | AX9: =Settings!$I16 -> CL | AY9: =Settings!$I17 -> SHL
D10: =Settings!D4 -> EMP001 | E10: =IFERROR(VLOOKUP(D10,Settings!D4:F20,2,FALSE),"") -> Aarav Sharma | F10: Recruitment | G10: =IFERROR(VLOOKUP(D10,Settings!D4:F20,3,FALSE),"") -> Software Engineer | H10: =IFERROR(VLOOKUP(E10,Settings!E4:G20,3,FALSE),"") -> Engineering | AN10: =COUNTIF($I10:$AM10,"=P") -> 0 | AO10: =COUNTIF($I10:$AM10,"=EL") -> 0 | AP10: =COUNTIF($I10:$AM10,"=SL") -> 0 | AQ10: =COUNTIF($I10:$AM10,"=MPL") -> 0 | AR10: =COUNTIF($I10:$AM10,"=HD") -> 0 | AS10: =COUNTIF($I10:$AM10,"=WFH") -> 0 | AT10: =COUNTIF($I10:$AM10,"=H") -> 0 | AU10: =COUNTIF($I10:$AM10,"=WO") -> 0 | AV10: =COUNTIF($I10:$AM10,"=A") -> 0 | AW10: =COUNTIF($I10:$AM10,"=LT") -> 0 | AX10: =COUNTIF($I10:$AM10,"=CL") -> 0 | AY10: =COUNTIF($I10:$AM10,"=SHL") -> 0 | AZ10: =IF(E10<>"",SUM(AO10,AP10,AQ10,AX10,AY10),"") -> 0 | BA10: =IF(E10<>"",AN10+AO10+AP10+AQ10+0.05*AR10+AS10+AT10+AU10+AX10+AY10) -> 0 | BB10: 0 | BC10: =IF(E$10<>"",ROUND(BB10/COUNTA($I$9:$AM$9)*$BA10,2),"") -> 0 | BD10: =BC10+BE10 -> 0 | BE10: {=SUMPRODUCT((TEXT($I$7:$AM$8,"dddd")="Sun")*($I10:$AM10="P")*(BB10/28))} -> 0
D11: =Settings!D5 -> EMP002 | E11: =IFERROR(VLOOKUP(D11,Settings!D5:F21,2,FALSE),"") -> Priya Verma | F11: Recruitment | G11: =IFERROR(VLOOKUP(D11,Settings!D5:F21,3,FALSE),"") -> Data Analyst | H11: =IFERROR(VLOOKUP(E11,Settings!E5:G21,3,FALSE),"") -> Analytics | AN11: =COUNTIF($I11:$AM11,"=P") -> 0 | AO11: =COUNTIF($I11:$AM11,"=EL") -> 0 | AP11: =COUNTIF($I11:$AM11,"=SL") -> 0 | AQ11: =COUNTIF($I11:$AM11,"=MPL") -> 0 | AR11: =COUNTIF($I11:$AM11,"=HD") -> 0 | AS11: =COUNTIF($I11:$AM11,"=WFH") -> 0 | AT11: =COUNTIF($I11:$AM11,"=H") -> 0 | AU11: =COUNTIF($I11:$AM11,"=WO") -> 0 | AV11: =COUNTIF($I11:$AM11,"=A") -> 0 | AW11: =COUNTIF($I11:$AM11,"=LT") -> 0 | AX11: =COUNTIF($I11:$AM11,"=CL") -> 0 | AY11: =COUNTIF($I11:$AM11,"=SHL") -> 0 | AZ11: =IF(E11<>"",SUM(AO11,AP11,AQ11,AX11,AY11),"") -> 0 | BA11: =IF(E11<>"",AN11+AO11+AP11+AQ11+0.05*AR11+AS11+AT11+AU11+AX11+AY11) -> 0 | BB11: 0 | BC11: =IF(E$10<>"",ROUND(BB11/COUNTA($I$9:$AM$9)*$BA11,2),"") -> 0 | BD11: =BC11+BE11 -> 0 | BE11: {=SUMPRODUCT((TEXT($I$7:$AM$8,"dddd")="Sun")*($I11:$AM11="P")*(BB11/28))} -> 0
D12: =Settings!D6 -> EMP003 | E12: =IFERROR(VLOOKUP(D12,Settings!D6:F22,2,FALSE),"") -> Rohan Gupta | F12: Recruitment | G12: =IFERROR(VLOOKUP(D12,Settings!D6:F22,3,FALSE),"") -> Product Manager | H12: =IFERROR(VLOOKUP(E12,Settings!E6:G22,3,FALSE),"") -> Product | AN12: =COUNTIF($I12:$AM12,"=P") -> 0 | AO12: =COUNTIF($I12:$AM12,"=EL") -> 0 | AP12: =COUNTIF($I12:$AM12,"=SL") -> 0 | AQ12: =COUNTIF($I12:$AM12,"=MPL") -> 0 | AR12: =COUNTIF($I12:$AM12,"=HD") -> 0 | AS12: =COUNTIF($I12:$AM12,"=WFH") -> 0 | AT12: =COUNTIF($I12:$AM12,"=H") -> 0 | AU12: =COUNTIF($I12:$AM12,"=WO") -> 0 | AV12: =COUNTIF($I12:$AM12,"=A") -> 0 | AW12: =COUNTIF($I12:$AM12,"=LT") -> 0 | AX12: =COUNTIF($I12:$AM12,"=CL") -> 0 | AY12: =COUNTIF($I12:$AM12,"=SHL") -> 0 | AZ12: =IF(E12<>"",SUM(AO12,AP12,AQ12,AX12,AY12),"") -> 0 | BA12: =IF(E12<>"",AN12+AO12+AP12+AQ12+0.05*AR12+AS12+AT12+AU12+AX12+AY12) -> 0 | BB12: 0 | BC12: =IF(E$10<>"",ROUND(BB12/COUNTA($I$9:$AM$9)*$BA12,2),"") -> 0 | BD12: =BC12+BE12 -> 0 | BE12: {=SUMPRODUCT((TEXT($I$7:$AM$8,"dddd")="Sun")*($I12:$AM12="P")*(BB12/28))} -> 0
D13: =Settings!D7 -> EMP004 | E13: =IFERROR(VLOOKUP(D13,Settings!D7:F23,2,FALSE),"") -> Ananya Iyer | F13: Recruitment | G13: =IFERROR(VLOOKUP(D13,Settings!D7:F23,3,FALSE),"") -> UX/UI Designer | H13: =IFERROR(VLOOKUP(E13,Settings!E7:G23,3,FALSE),"") -> Design | AN13: =COUNTIF($I13:$AM13,"=P") -> 0 | AO13: =COUNTIF($I13:$AM13,"=EL") -> 0 | AP13: =COUNTIF($I13:$AM13,"=SL") -> 0 | AQ13: =COUNTIF($I13:$AM13,"=MPL") -> 0 | AR13: =COUNTIF($I13:$AM13,"=HD") -> 0 | AS13: =COUNTIF($I13:$AM13,"=WFH") -> 0 | AT13: =COUNTIF($I13:$AM13,"=H") -> 0 | AU13: =COUNTIF($I13:$AM13,"=WO") -> 0 | AV13: =COUNTIF($I13:$AM13,"=A") -> 0 | AW13: =COUNTIF($I13:$AM13,"=LT") -> 0 | AX13: =COUNTIF($I13:$AM13,"=CL") -> 0 | AY13: =COUNTIF($I13:$AM13,"=SHL") -> 0 | AZ13: =IF(E13<>"",SUM(AO13,AP13,AQ13,AX13,AY13),"") -> 0 | BA13: =IF(E13<>"",AN13+AO13+AP13+AQ13+0.05*AR13+AS13+AT13+AU13+AX13+AY13) -> 0 | BB13: 0 | BC13: =IF(E$10<>"",ROUND(BB13/COUNTA($I$9:$AM$9)*$BA13,2),"") -> 0 | BD13: =BC13+BE13 -> 0 | BE13: {=SUMPRODUCT((TEXT($I$7:$AM$8,"dddd")="Sun")*($I13:$AM13="P")*(BB13/28))} -> 0
D14: =Settings!D8 -> EMP005 | E14: =IFERROR(VLOOKUP(D14,Settings!D8:F24,2,FALSE),"") -> Vikram Malhotra | F14: Recruitment | G14: =IFERROR(VLOOKUP(D14,Settings!D8:F24,3,FALSE),"") -> Senior Developer | H14: =IFERROR(VLOOKUP(E14,Settings!E8:G24,3,FALSE),"") -> Engineering | AN14: =COUNTIF($I14:$AM14,"=P") -> 0 | AO14: =COUNTIF($I14:$AM14,"=EL") -> 0 | AP14: =COUNTIF($I14:$AM14,"=SL") -> 0 | AQ14: =COUNTIF($I14:$AM14,"=MPL") -> 0 | AR14: =COUNTIF($I14:$AM14,"=HD") -> 0 | AS14: =COUNTIF($I14:$AM14,"=WFH") -> 0 | AT14: =COUNTIF($I14:$AM14,"=H") -> 0 | AU14: =COUNTIF($I14:$AM14,"=WO") -> 0 | AV14: =COUNTIF($I14:$AM14,"=A") -> 0 | AW14: =COUNTIF($I14:$AM14,"=LT") -> 0 | AX14: =COUNTIF($I14:$AM14,"=CL") -> 0 | AY14: =COUNTIF($I14:$AM14,"=SHL") -> 0 | AZ14: =IF(E14<>"",SUM(AO14,AP14,AQ14,AX14,AY14),"") -> 0 | BA14: =IF(E14<>"",AN14+AO14+AP14+AQ14+0.05*AR14+AS14+AT14+AU14+AX14+AY14) -> 0 | BB14: 0 | BC14: =IF(E$10<>"",ROUND(BB14/COUNTA($I$9:$AM$9)*$BA14,2),"") -> 0 | BD14: =BC14+BE14 -> 0 | BE14: {=SUMPRODUCT((TEXT($I$7:$AM$8,"dddd")="Sun")*($I14:$AM14="P")*(BB14/28))} -> 0
D15: =Settings!D9 -> EMP006 | E15: =IFERROR(VLOOKUP(D15,Settings!D9:F25,2,FALSE),"") -> Neha Singh | F15: Recruitment | G15: =IFERROR(VLOOKUP(D15,Settings!D9:F25,3,FALSE),"") -> HR Generalist | H15: =IFERROR(VLOOKUP(E15,Settings!E9:G25,3,FALSE),"") -> Human Resources | AN15: =COUNTIF($I15:$AM15,"=P") -> 0 | AO15: =COUNTIF($I15:$AM15,"=EL") -> 0 | AP15: =COUNTIF($I15:$AM15,"=SL") -> 0 | AQ15: =COUNTIF($I15:$AM15,"=MPL") -> 0 | AR15: =COUNTIF($I15:$AM15,"=HD") -> 0 | AS15: =COUNTIF($I15:$AM15,"=WFH") -> 0 | AT15: =COUNTIF($I15:$AM15,"=H") -> 0 | AU15: =COUNTIF($I15:$AM15,"=WO") -> 0 | AV15: =COUNTIF($I15:$AM15,"=A") -> 0 | AW15: =COUNTIF($I15:$AM15,"=LT") -> 0 | AX15: =COUNTIF($I15:$AM15,"=CL") -> 0 | AY15: =COUNTIF($I15:$AM15,"=SHL") -> 0 | AZ15: =IF(E15<>"",SUM(AO15,AP15,AQ15,AX15,AY15),"") -> 0 | BA15: =IF(E15<>"",AN15+AO15+AP15+AQ15+0.05*AR15+AS15+AT15+AU15+AX15+AY15) -> 0 | BB15: 0 | BC15: =IF(E$10<>"",ROUND(BB15/COUNTA($I$9:$AM$9)*$BA15,2),"") -> 0 | BD15: =BC15+BE15 -> 0 | BE15: {=SUMPRODUCT((TEXT($I$7:$AM$8,"dddd")="Sun")*($I15:$AM15="P")*(BB15/28))} -> 0
D16: =Settings!D10 -> EMP007 | E16: =IFERROR(VLOOKUP(D16,Settings!D10:F26,2,FALSE),"") -> Amit Patel | F16: Recruitment | G16: =IFERROR(VLOOKUP(D16,Settings!D10:F26,3,FALSE),"") -> Financial Analyst | H16: =IFERROR(VLOOKUP(E16,Settings!E10:G26,3,FALSE),"") -> Finance | AN16: =COUNTIF($I16:$AM16,"=P") -> 0 | AO16: =COUNTIF($I16:$AM16,"=EL") -> 0 | AP16: =COUNTIF($I16:$AM16,"=SL") -> 0 | AQ16: =COUNTIF($I16:$AM16,"=MPL") -> 0 | AR16: =COUNTIF($I16:$AM16,"=HD") -> 0 | AS16: =COUNTIF($I16:$AM16,"=WFH") -> 0 | AT16: =COUNTIF($I16:$AM16,"=H") -> 0 | AU16: =COUNTIF($I16:$AM16,"=WO") -> 0 | AV16: =COUNTIF($I16:$AM16,"=A") -> 0 | AW16: =COUNTIF($I16:$AM16,"=LT") -> 0 | AX16: =COUNTIF($I16:$AM16,"=CL") -> 0 | AY16: =COUNTIF($I16:$AM16,"=SHL") -> 0 | AZ16: =IF(E16<>"",SUM(AO16,AP16,AQ16,AX16,AY16),"") -> 0 | BA16: =IF(E16<>"",AN16+AO16+AP16+AQ16+0.05*AR16+AS16+AT16+AU16+AX16+AY16) -> 0 | BB16: 0 | BC16: =IF(E$10<>"",ROUND(BB16/COUNTA($I$9:$AM$9)*$BA16,2),"") -> 0 | BD16: =BC16+BE16 -> 0 | BE16: {=SUMPRODUCT((TEXT($I$7:$AM$8,"dddd")="Sun")*($I16:$AM16="P")*(BB16/28))} -> 0
D17: =Settings!D11 -> EMP008 | E17: =IFERROR(VLOOKUP(D17,Settings!D11:F27,2,FALSE),"") -> Sneha Joshi | F17: Recruitment | G17: =IFERROR(VLOOKUP(D17,Settings!D11:F27,3,FALSE),"") -> Marketing Specialist | H17: =IFERROR(VLOOKUP(E17,Settings!E11:G27,3,FALSE),"") -> Marketing | AN17: =COUNTIF($I17:$AM17,"=P") -> 0 | AO17: =COUNTIF($I17:$AM17,"=EL") -> 0 | AP17: =COUNTIF($I17:$AM17,"=SL") -> 0 | AQ17: =COUNTIF($I17:$AM17,"=MPL") -> 0 | AR17: =COUNTIF($I17:$AM17,"=HD") -> 0 | AS17: =COUNTIF($I17:$AM17,"=WFH") -> 0 | AT17: =COUNTIF($I17:$AM17,"=H") -> 0 | AU17: =COUNTIF($I17:$AM17,"=WO") -> 0 | AV17: =COUNTIF($I17:$AM17,"=A") -> 0 | AW17: =COUNTIF($I17:$AM17,"=LT") -> 0 | AX17: =COUNTIF($I17:$AM17,"=CL") -> 0 | AY17: =COUNTIF($I17:$AM17,"=SHL") -> 0 | AZ17: =IF(E17<>"",SUM(AO17,AP17,AQ17,AX17,AY17),"") -> 0 | BA17: =IF(E17<>"",AN17+AO17+AP17+AQ17+0.05*AR17+AS17+AT17+AU17+AX17+AY17) -> 0 | BB17: 0 | BC17: =IF(E$10<>"",ROUND(BB17/COUNTA($I$9:$AM$9)*$BA17,2),"") -> 0 | BD17: =BC17+BE17 -> 0 | BE17: {=SUMPRODUCT((TEXT($I$7:$AM$8,"dddd")="Sun")*($I17:$AM17="P")*(BB17/28))} -> 0
D18: =Settings!D12 -> EMP009 | E18: =IFERROR(VLOOKUP(D18,Settings!D12:F28,2,FALSE),"") -> Rahul Mehta | F18: Recruitment | G18: =IFERROR(VLOOKUP(D18,Settings!D12:F28,3,FALSE),"") -> DevOps Engineer | H18: =IFERROR(VLOOKUP(E18,Settings!E12:G28,3,FALSE),"") -> Engineering | AN18: =COUNTIF($I18:$AM18,"=P") -> 0 | AO18: =COUNTIF($I18:$AM18,"=EL") -> 0 | AP18: =COUNTIF($I18:$AM18,"=SL") -> 0 | AQ18: =COUNTIF($I18:$AM18,"=MPL") -> 0 | AR18: =COUNTIF($I18:$AM18,"=HD") -> 0 | AS18: =COUNTIF($I18:$AM18,"=WFH") -> 0 | AT18: =COUNTIF($I18:$AM18,"=H") -> 0 | AU18: =COUNTIF($I18:$AM18,"=WO") -> 0 | AV18: =COUNTIF($I18:$AM18,"=A") -> 0 | AW18: =COUNTIF($I18:$AM18,"=LT") -> 0 | AX18: =COUNTIF($I18:$AM18,"=CL") -> 0 | AY18: =COUNTIF($I18:$AM18,"=SHL") -> 0 | AZ18: =IF(E18<>"",SUM(AO18,AP18,AQ18,AX18,AY18),"") -> 0 | BA18: =IF(E18<>"",AN18+AO18+AP18+AQ18+0.05*AR18+AS18+AT18+AU18+AX18+AY18) -> 0 | BB18: 0 | BC18: =IF(E$10<>"",ROUND(BB18/COUNTA($I$9:$AM$9)*$BA18,2),"") -> 0 | BD18: =BC18+BE18 -> 0 | BE18: {=SUMPRODUCT((TEXT($I$7:$AM$8,"dddd")="Sun")*($I18:$AM18="P")*(BB18/28))} -> 0
D19: =Settings!D13 -> EMP010 | E19: =IFERROR(VLOOKUP(D19,Settings!D13:F29,2,FALSE),"") -> Pooja Nair | F19: Recruitment | G19: =IFERROR(VLOOKUP(D19,Settings!D13:F29,3,FALSE),"") -> QA Automation Engineer | H19: =IFERROR(VLOOKUP(E19,Settings!E13:G29,3,FALSE),"") -> Quality Assurance | AN19: =COUNTIF($I19:$AM19,"=P") -> 0 | AO19: =COUNTIF($I19:$AM19,"=EL") -> 0 | AP19: =COUNTIF($I19:$AM19,"=SL") -> 0 | AQ19: =COUNTIF($I19:$AM19,"=MPL") -> 0 | AR19: =COUNTIF($I19:$AM19,"=HD") -> 0 | AS19: =COUNTIF($I19:$AM19,"=WFH") -> 0 | AT19: =COUNTIF($I19:$AM19,"=H") -> 0 | AU19: =COUNTIF($I19:$AM19,"=WO") -> 0 | AV19: =COUNTIF($I19:$AM19,"=A") -> 0 | AW19: =COUNTIF($I19:$AM19,"=LT") -> 0 | AX19: =COUNTIF($I19:$AM19,"=CL") -> 0 | AY19: =COUNTIF($I19:$AM19,"=SHL") -> 0 | AZ19: =IF(E19<>"",SUM(AO19,AP19,AQ19,AX19,AY19),"") -> 0 | BA19: =IF(E19<>"",AN19+AO19+AP19+AQ19+0.05*AR19+AS19+AT19+AU19+AX19+AY19) -> 0 | BB19: 0 | BC19: =IF(E$10<>"",ROUND(BB19/COUNTA($I$9:$AM$9)*$BA19,2),"") -> 0 | BD19: =BC19+BE19 -> 0 | BE19: {=SUMPRODUCT((TEXT($I$7:$AM$8,"dddd")="Sun")*($I19:$AM19="P")*(BB19/28))} -> 0
D20: =Settings!D14 -> EMP011 | E20: =IFERROR(VLOOKUP(D20,Settings!D14:F30,2,FALSE),"") -> Karan Kapoor | F20: Recruitment | G20: =IFERROR(VLOOKUP(D20,Settings!D14:F30,3,FALSE),"") -> Content Strategist | H20: =IFERROR(VLOOKUP(E20,Settings!E14:G30,3,FALSE),"") -> Marketing | AN20: =COUNTIF($I20:$AM20,"=P") -> 0 | AO20: =COUNTIF($I20:$AM20,"=EL") -> 0 | AP20: =COUNTIF($I20:$AM20,"=SL") -> 0 | AQ20: =COUNTIF($I20:$AM20,"=MPL") -> 0 | AR20: =COUNTIF($I20:$AM20,"=HD") -> 0 | AS20: =COUNTIF($I20:$AM20,"=WFH") -> 0 | AT20: =COUNTIF($I20:$AM20,"=H") -> 0 | AU20: =COUNTIF($I20:$AM20,"=WO") -> 0 | AV20: =COUNTIF($I20:$AM20,"=A") -> 0 | AW20: =COUNTIF($I20:$AM20,"=LT") -> 0 | AX20: =COUNTIF($I20:$AM20,"=CL") -> 0 | AY20: =COUNTIF($I20:$AM20,"=SHL") -> 0 | AZ20: =IF(E20<>"",SUM(AO20,AP20,AQ20,AX20,AY20),"") -> 0 | BA20: =IF(E20<>"",AN20+AO20+AP20+AQ20+0.05*AR20+AS20+AT20+AU20+AX20+AY20) -> 0 | BB20: 0 | BC20: =IF(E$10<>"",ROUND(BB20/COUNTA($I$9:$AM$9)*$BA20,2),"") -> 0 | BD20: =BC20+BE20 -> 0 | BE20: {=SUMPRODUCT((TEXT($I$7:$AM$8,"dddd")="Sun")*($I20:$AM20="P")*(BB20/28))} -> 0
D21: =Settings!D15 -> EMP012 | E21: =IFERROR(VLOOKUP(D21,Settings!D15:F31,2,FALSE),"") -> Ritu Sen | F21: Recruitment | G21: =IFERROR(VLOOKUP(D21,Settings!D15:F31,3,FALSE),"") -> Business Analyst | H21: =IFERROR(VLOOKUP(E21,Settings!E15:G31,3,FALSE),"") -> Strategy | AN21: =COUNTIF($I21:$AM21,"=P") -> 0 | AO21: =COUNTIF($I21:$AM21,"=EL") -> 0 | AP21: =COUNTIF($I21:$AM21,"=SL") -> 0 | AQ21: =COUNTIF($I21:$AM21,"=MPL") -> 0 | AR21: =COUNTIF($I21:$AM21,"=HD") -> 0 | AS21: =COUNTIF($I21:$AM21,"=WFH") -> 0 | AT21: =COUNTIF($I21:$AM21,"=H") -> 0 | AU21: =COUNTIF($I21:$AM21,"=WO") -> 0 | AV21: =COUNTIF($I21:$AM21,"=A") -> 0 | AW21: =COUNTIF($I21:$AM21,"=LT") -> 0 | AX21: =COUNTIF($I21:$AM21,"=CL") -> 0 | AY21: =COUNTIF($I21:$AM21,"=SHL") -> 0 | AZ21: =IF(E21<>"",SUM(AO21,AP21,AQ21,AX21,AY21),"") -> 0 | BA21: =IF(E21<>"",AN21+AO21+AP21+AQ21+0.05*AR21+AS21+AT21+AU21+AX21+AY21) -> 0 | BB21: 0 | BC21: =IF(E$10<>"",ROUND(BB21/COUNTA($I$9:$AM$9)*$BA21,2),"") -> 0 | BD21: =BC21+BE21 -> 0 | BE21: {=SUMPRODUCT((TEXT($I$7:$AM$8,"dddd")="Sun")*($I21:$AM21="P")*(BB21/28))} -> 0
... D28: =Settings!D22 -> EMP019 | E28: =IFERROR(VLOOKUP(D28,Settings!D22:F38,2,FALSE),"") -> Kunal Roy | F28: Recruitment | G28: =IFERROR(VLOOKUP(D28,Settings!D22:F38,3,FALSE),"") -> Frontend Developer | H28: =IFERROR(VLOOKUP(E28,Settings!E22:G38,3,FALSE),"") -> Engineering | AN28: =COUNTIF($I28:$AM28,"=P") -> 0 | AO28: =COUNTIF($I28:$AM28,"=EL") -> 0 | AP28: =COUNTIF($I28:$AM28,"=SL") -> 0 | AQ28: =COUNTIF($I28:$AM28,"=MPL") -> 0 | AR28: =COUNTIF($I28:$AM28,"=HD") -> 0 | AS28: =COUNTIF($I28:$AM28,"=WFH") -> 0 | AT28: =COUNTIF($I28:$AM28,"=H") -> 0 | AU28: =COUNTIF($I28:$AM28,"=WO") -> 0 | AV28: =COUNTIF($I28:$AM28,"=A") -> 0 | AW28: =COUNTIF($I28:$AM28,"=LT") -> 0 | AX28: =COUNTIF($I28:$AM28,"=CL") -> 0 | AY28: =COUNTIF($I28:$AM28,"=SHL") -> 0 | AZ28: =IF(E28<>"",SUM(AO28,AP28,AQ28,AX28,AY28),"") -> 0 | BA28: =IF(E28<>"",AN28+AO28+AP28+AQ28+0.05*AR28+AS28+AT28+AU28+AX28+AY28) -> 0 | BB28: 0 | BC28: =IF(E$10<>"",ROUND(BB28/COUNTA($I$9:$AM$9)*$BA28,2),"") -> 0 | BD28: =BC28+BE28 -> 0 | BE28: {=SUMPRODUCT((TEXT($I$7:$AM$8,"dddd")="Sun")*($I28:$AM28="P")*(BB28/28))} -> 0

Sheet Settings
A3: Year | C3: Months | D3: Emp. ID | E3: Employee Name | F3: Designation | G3: Department
A4: 2026 | C4: January | D4: EMP001 | E4: Aarav Sharma | F4: Software Engineer | G4: Engineering | L4: Cost Centre
A5: 2027 | C5: February | D5: EMP002 | E5: Priya Verma | F5: Data Analyst | G5: Analytics | H5: Words | I5: Code | L5: Recruitment
A6: 2028 | C6: March | D6: EMP003 | E6: Rohan Gupta | F6: Product Manager | G6: Product | H6: Present | I6: P | L6: M&A
C7: April | D7: EMP004 | E7: Ananya Iyer | F7: UX/UI Designer | G7: Design | H7: Earned Leave | I7: EL | L7: Skrilz
C8: May | D8: EMP005 | E8: Vikram Malhotra | F8: Senior Developer | G8: Engineering | H8: Sick Leave | I8: SL
C9: June | D9: EMP006 | E9: Neha Singh | F9: HR Generalist | G9: Human Resources | H9: Maternity or Paternity | I9: MPL
C10: July | D10: EMP007 | E10: Amit Patel | F10: Financial Analyst | G10: Finance | H10: Half Day | I10: HD
C11: August | D11: EMP008 | E11: Sneha Joshi | F11: Marketing Specialist | G11: Marketing | H11: Work From Home | I11: WFH
C12: September | D12: EMP009 | E12: Rahul Mehta | F12: DevOps Engineer | G12: Engineering | H12: Holidays | I12: H
C13: October | D13: EMP010 | E13: Pooja Nair | F13: QA Automation Engineer | G13: Quality Assurance | H13: Week Offs | I13: WO
C14: November | D14: EMP011 | E14: Karan Kapoor | F14: Content Strategist | G14: Marketing | H14: Absent / No Show | I14: A
C15: December | D15: EMP012 | E15: Ritu Sen | F15: Business Analyst | G15: Strategy | H15: Left | I15: LT
D16: EMP013 | E16: Manish Kulkarni | F16: System Administrator | G16: IT Support | H16: Casual Leaves | I16: CL
D17: EMP014 | E17: Divya Pillai | F17: Legal Advisor | G17: Legal | H17: Short Leaves | I17: SHL
D18: EMP015 | E18: Sameer Khan | F18: Sales Manager | G18: Sales
D19: EMP016 | E19: Pooja Rao | F19: Customer Support Lead | G19: Customer Success
D20: EMP017 | E20: Alok Tiwari | F20: Operations Manager | G20: Operations
D21: EMP018 | E21: Tanvi Deshmukh | F21: Accountant | G21: Finance
D22: EMP019 | E22: Kunal Roy | F22: Frontend Developer | G22: Engineering
